MS23056UNO/__init__.py
MS23056UNO/biseccion.py
MS23056UNO/cramer.py
MS23056UNO/gauss.py
MS23056UNO/gauss_jordan.py
MS23056UNO/gauss_seidel.py
MS23056UNO/jacobi.py
MS23056UNO/lu.py
ms23056uno-0.1.1.dist-info/licenses/LICENSE
ms23056uno-0.1.1.dist-info/METADATA
ms23056uno-0.1.1.dist-info/WHEEL
ms23056uno-0.1.1.dist-info/top_level.txt
ms23056uno-0.1.1.dist-info/RECORD
