Metadata-Version: 2.4
Name: MS23056UNO
Version: 0.1.1
Summary: Librería para resolver sistemas de ecuaciones lineales y no lineales
Home-page: https://github.com/MOiUES23/MS230565UNO
Author: Moises Jonathan Martinez Saravia
Author-email: ms23056@ues.edu.sv
Classifier: Programming Language :: Python :: 3
Classifier: Operating System :: OS Independent
Requires-Python: >=3.6
License-File: LICENSE
Requires-Dist: numpy
Requires-Dist: scipy
Dynamic: author
Dynamic: author-email
Dynamic: classifier
Dynamic: description
Dynamic: description-content-type
Dynamic: home-page
Dynamic: license-file
Dynamic: requires-dist
Dynamic: requires-python
Dynamic: summary
